{"sug_list":[{"pos":[{"begin":0,"end":8}],"content":"tatu tyni","sug_type":"","word_record":{"group_id":"8188439936410400668","words_position":0,"words_content":"tatu tyni","words_source":"sug"},"extra_info":{"cut_query":"[\"tatu\",\"tyni\"]","is_history_sug":"0","is_personalized":"1","lang":"pl","recall_reason":"origin_query|tiktok_orion_query"},"rich_sug_sec_pos":null,"highlight_pos":null},{"pos":[{"begin":0,"end":3}],"content":"tatu","sug_type":"","word_record":{"group_id":"9002048970787286704","words_position":1,"words_content":"tatu","words_source":"sug"},"extra_info":{"cut_query":"[\"tatu\"]","is_history_sug":"0","is_personalized":"1","lang":"sw","recall_reason":"orion_qse_recall"},"rich_sug_sec_pos":null,"highlight_pos":null},{"pos":[{"begin":0,"end":3}],"content":"tatu1065","sug_type":"","word_record":{"group_id":"7579886446889921660","words_position":2,"words_content":"tatu1065","words_source":"sug"},"extra_info":{"cut_query":"[\"tatu\",\"1065\"]","is_personalized":"1","lang":"sw","recall_reason":"orion_qse_recall"},"rich_sug_sec_pos":null,"highlight_pos":null},{"pos":[{"begin":4,"end":6},{"begin":9,"end":9},{"begin":14,"end":14}],"content":"signature for tatu","sug_type":"","word_record":{"group_id":"2501231106672527406","words_position":3,"words_content":"signature for tatu","words_source":"sug"},"extra_info":{"cut_query":"[\"signature\",\"for\",\"tatu\"]","is_personalized":"1","lang":"en","recall_reason":"query_xlmr_viking_proxy_recall"},"rich_sug_sec_pos":null,"highlight_pos":null},{"pos":[{"begin":0,"end":4},{"begin":7,"end":7},{"begin":10,"end":10}],"content":"tatu sandvik","sug_type":"","word_record":{"group_id":"1522905754591177606","words_position":4,"words_content":"tatu sandvik","words_source":"sug"},"extra_info":{"cut_query":"[\"tatu\",\"sandvik\"]","is_personalized":"1","lang":"no","recall_reason":"orion_qse_recall"},"rich_sug_sec_pos":null,"highlight_pos":null},{"pos":[{"begin":0,"end":4},{"begin":11,"end":11}],"content":"tatu kamppinen","sug_type":"","word_record":{"group_id":"3955766744678903329","words_position":5,"words_content":"tatu kamppinen","words_source":"sug"},"extra_info":{"cut_query":"[\"tatu\",\"kamppinen\"]","is_personalized":"1","lang":"fi","recall_reason":"orion_qse_recall"},"rich_sug_sec_pos":null,"highlight_pos":null},{"pos":[{"begin":2,"end":5}],"content":"88tatu","sug_type":"","word_record":{"group_id":"9099657566715175769","words_position":6,"words_content":"88tatu","words_source":"sug"},"extra_info":{"cut_query":"[\"88\",\"tatu\"]","is_personalized":"1","lang":"sw","recall_reason":"orion_qse_recall"},"rich_sug_sec_pos":null,"highlight_pos":null},{"pos":[{"begin":0,"end":4},{"begin":8,"end":9}],"content":"tatu ristimaki","sug_type":"","word_record":{"group_id":"3049434699923078797","words_position":7,"words_content":"tatu ristimaki","words_source":"sug"},"extra_info":{"cut_query":"[\"tatu\",\"ristimaki\"]","is_personalized":"1","lang":"ms","recall_reason":"orion_qse_recall"},"rich_sug_sec_pos":null,"highlight_pos":null}],"status_code":0,"status_msg":"","rid":"2024061114382824FAB1C366DD21465EFC","words_query_record":{"info":"{}","words_source":"sug","query_id":""},"extra":{"now":1718116709000,"logid":"2024061114382824FAB1C366DD21465EFC","fatal_item_ids":[],"search_request_id":"","api_debug_info":null},"log_pb":{"impr_id":"2024061114382824FAB1C366DD21465EFC"},"user_input_query":"Tatu Tyni"}