{"sug_list":[{"pos":[{"begin":0,"end":11}],"content":"jussi saramo","sug_type":"","word_record":{"group_id":"2431477757261578979","words_position":0,"words_content":"jussi saramo","words_source":"sug"},"extra_info":{"cut_query":"[\"jussi\",\"saramo\"]","is_history_sug":"0","is_personalized":"1","lang":"fi","recall_reason":"tiktok_orion_search_session|origin_query|orion_qse_recall|tiktok_index_active_7d_query|tiktok_index_global_active_7d_query|tiktok_orion_query"},"rich_sug_sec_pos":null,"highlight_pos":null},{"pos":[{"begin":9,"end":15},{"begin":17,"end":18}],"content":"stand up jussi simola","sug_type":"","word_record":{"group_id":"2695532698365164861","words_position":1,"words_content":"stand up jussi simola","words_source":"sug"},"extra_info":{"cut_query":"[\"stand\",\"up\",\"jussi\",\"simola\"]","is_history_sug":"0","is_personalized":"1","lang":"en","recall_reason":"orion_qse_recall"},"rich_sug_sec_pos":null,"highlight_pos":null},{"pos":[{"begin":0,"end":5},{"begin":16,"end":17},{"begin":19,"end":19}],"content":"jussi hallaho n sana","sug_type":"","word_record":{"group_id":"4441831086822627095","words_position":2,"words_content":"jussi hallaho n sana","words_source":"sug"},"extra_info":{"cut_query":"[\"jussi\",\"hallaho\",\"n\",\"sana\"]","is_personalized":"1","lang":"id","recall_reason":"orion_qse_recall"},"rich_sug_sec_pos":null,"highlight_pos":null},{"pos":[{"begin":0,"end":4}],"content":"jussi","sug_type":"","word_record":{"group_id":"259260243097747651","words_position":3,"words_content":"jussi","words_source":"sug"},"extra_info":{"cut_query":"[\"jussi\"]","is_personalized":"1","lang":"fi","recall_reason":"orion_qse_recall"},"rich_sug_sec_pos":null,"highlight_pos":null},{"pos":[{"begin":0,"end":6},{"begin":8,"end":9}],"content":"jussi simola","sug_type":"","word_record":{"group_id":"810631911955153908","words_position":4,"words_content":"jussi simola","words_source":"sug"},"extra_info":{"cut_query":"[\"jussi\",\"simola\"]","is_personalized":"1","lang":"fi","recall_reason":"orion_qse_recall"},"rich_sug_sec_pos":null,"highlight_pos":null},{"pos":[{"begin":0,"end":10}],"content":"jussi sarama","sug_type":"","word_record":{"group_id":"1982555372798952749","words_position":5,"words_content":"jussi sarama","words_source":"sug"},"extra_info":{"cut_query":"[\"jussi\",\"sarama\"]","is_personalized":"1","lang":"id","recall_reason":"tiktok_orion_query"},"rich_sug_sec_pos":null,"highlight_pos":null},{"pos":[{"begin":0,"end":5},{"begin":7,"end":7},{"begin":10,"end":10},{"begin":14,"end":14}],"content":"jussi halla aho edit","sug_type":"","word_record":{"group_id":"8040845032874207466","words_position":6,"words_content":"jussi halla aho edit","words_source":"sug"},"extra_info":{"cut_query":"[\"jussi\",\"halla\",\"aho\",\"edit\"]","is_personalized":"1","lang":"es","recall_reason":"orion_qse_recall"},"rich_sug_sec_pos":null,"highlight_pos":null},{"pos":[{"begin":0,"end":5},{"begin":11,"end":12}],"content":"jussi kukkurainen","sug_type":"","word_record":{"group_id":"7151333719678704059","words_position":7,"words_content":"jussi kukkurainen","words_source":"sug"},"extra_info":{"cut_query":"[\"jussi\",\"kukkurainen\"]","is_personalized":"1","lang":"ja","recall_reason":"orion_qse_recall"},"rich_sug_sec_pos":null,"highlight_pos":null}],"status_code":0,"status_msg":"","rid":"2024061707351275345F880D3E900502D3","words_query_record":{"info":"{}","words_source":"sug","query_id":""},"extra":{"now":1718609713000,"logid":"2024061707351275345F880D3E900502D3","fatal_item_ids":[],"search_request_id":"","api_debug_info":null},"log_pb":{"impr_id":"2024061707351275345F880D3E900502D3"},"user_input_query":"Jussi Saramo"}