{"sug_list":[{"pos":[{"begin":0,"end":12}],"content":"tarja filatov","sug_type":"","word_record":{"group_id":"1718403736869153085","words_position":0,"words_content":"tarja filatov","words_source":"sug"},"extra_info":{"cut_query":"[\"tarja\",\"filatov\"]","is_history_sug":"0","is_personalized":"1","lang":"sl","recall_reason":"origin_query|tiktok_orion_search_session|tiktok_index_active_7d_query|tiktok_orion_query|tiktok_index_global_active_7d_query"},"rich_sug_sec_pos":null,"highlight_pos":null},{"pos":[{"begin":0,"end":4}],"content":"tarja69","sug_type":"","word_record":{"group_id":"1330617912642239569","words_position":1,"words_content":"tarja69","words_source":"sug"},"extra_info":{"cut_query":"[\"tarja\",\"69\"]","is_history_sug":"0","is_personalized":"1","lang":"fi","recall_reason":"orion_qse_recall"},"rich_sug_sec_pos":null,"highlight_pos":null},{"pos":[{"begin":0,"end":4}],"content":"tarja","sug_type":"","word_record":{"group_id":"5904852826168529105","words_position":2,"words_content":"tarja","words_source":"sug"},"extra_info":{"cut_query":"[\"tarja\"]","is_personalized":"1","lang":"fi","recall_reason":"orion_qse_recall"},"rich_sug_sec_pos":null,"highlight_pos":null},{"pos":[{"begin":0,"end":6}],"content":"filatov","sug_type":"","word_record":{"group_id":"7090128506400597346","words_position":3,"words_content":"filatov","words_source":"sug"},"extra_info":{"cut_query":"[\"filatov\"]","is_personalized":"1","lang":"sl","recall_reason":"query_xlmr_viking_proxy_recall"},"rich_sug_sec_pos":null,"highlight_pos":null},{"pos":[{"begin":1,"end":7}],"content":"«filatov","sug_type":"","word_record":{"group_id":"1938569097736082403","words_position":4,"words_content":"«filatov","words_source":"sug"},"extra_info":{"cut_query":"[\"«\",\"filatov\"]","is_personalized":"1","lang":"no","recall_reason":"query_xlmr_viking_proxy_recall"},"rich_sug_sec_pos":null,"highlight_pos":null},{"pos":[{"begin":0,"end":6}],"content":"filatov3","sug_type":"","word_record":{"group_id":"278575324380513117","words_position":5,"words_content":"filatov3","words_source":"sug"},"extra_info":{"cut_query":"[\"filatov\",\"3\"]","is_personalized":"1","lang":"sl","recall_reason":"query_xlmr_viking_proxy_recall"},"rich_sug_sec_pos":null,"highlight_pos":null},{"pos":[{"begin":0,"end":6}],"content":"filatov20","sug_type":"","word_record":{"group_id":"256883302343501638","words_position":6,"words_content":"filatov20","words_source":"sug"},"extra_info":{"cut_query":"[\"filatov\",\"20\"]","is_personalized":"1","lang":"sl","recall_reason":"query_xlmr_viking_proxy_recall"},"rich_sug_sec_pos":null,"highlight_pos":null},{"pos":[{"begin":0,"end":5},{"begin":8,"end":9}],"content":"tarja halonen meme","sug_type":"","word_record":{"group_id":"7670408518229473093","words_position":7,"words_content":"tarja halonen meme","words_source":"sug"},"extra_info":{"cut_query":"[\"tarja\",\"halonen\",\"meme\"]","is_personalized":"1","lang":"es","recall_reason":"orion_qse_recall"},"rich_sug_sec_pos":null,"highlight_pos":null}],"status_code":0,"status_msg":"","rid":"20240617073450F9E9973503BC200498C2","words_query_record":{"info":"{}","words_source":"sug","query_id":""},"extra":{"now":1718609691000,"logid":"20240617073450F9E9973503BC200498C2","fatal_item_ids":[],"search_request_id":"","api_debug_info":null},"log_pb":{"impr_id":"20240617073450F9E9973503BC200498C2"},"user_input_query":"Tarja Filatov"}